README.md
beancount_interpolate/__init__.py
beancount_interpolate/common.py
beancount_interpolate/depreciate.py
beancount_interpolate/recur.py
beancount_interpolate/split.py
beancount_interpolate/spread.py
beancount_interpolate-2.5.0.dist-info/LICENSE
beancount_interpolate-2.5.0.dist-info/METADATA
beancount_interpolate-2.5.0.dist-info/WHEEL
beancount_interpolate-2.5.0.dist-info/top_level.txt
beancount_interpolate-2.5.0.dist-info/RECORD
