Metadata-Version: 2.1
Name: beancount-interpolate
Version: 2.5.0
Summary: Plugins for Beancount to interpolate transactions
Home-page: https://github.com/Akuukis/beancount_interpolate
Author: Akuukis
Author-email: akuukis@kalvis.lv
License: GNU GPLv3
Download-URL: https://pypi.python.org/pypi/beancount_interpolate
Platform: UNKNOWN
Requires-Dist: beancount (>=2.0)
Requires-Dist: beancount-plugin-utils (>=0.0.2)
